{
  "Defs": {
    "Marsh": {
      "collidable": false,
      "supportProvided": "Medium",
      "supportReq": "None",
      "graphicData": {
        "texturePath": "terrain/natural/marsh",
        "variants": 1,
        "color": {
          "R": 0.18039216,
          "G": 0.54509807,
          "B": 0.34117648,
          "A": 1.0,
          "R8": 46,
          "G8": 139,
          "B8": 87,
          "A8": 255,
          "H": 0.40681005,
          "S": 0.66906476,
          "V": 0.54509807,
          "Luminance": 0.45283842
        },
        "graphicSize": {
          "X": 16,
          "Y": 16
        }
      },
      "statSheet": {
        "Stats": {
          "fertility": {
            "defName": "fertility",
            "description": "The tile's fertility",
            "Type": "Undefined",
            "baseValue": 0.0
          }
        },
        "StatModifers": {
          "Move Speed": {
            "defName": "MoveSpeed Modifier",
            "description": "Tiles effect on Move Speed",
            "modifierType": "Flat",
            "targetStat": "Move Speed",
            "value": 0.4
          }
        }
      },
      "defName": "Marsh",
      "description": "it's Marshy"
    },
    "Shallow Ocean": {
      "collidable": false,
      "supportProvided": "Medium",
      "supportReq": "None",
      "graphicData": {
        "texturePath": "terrain/natural/ocean",
        "variants": 1,
        "color": {
          "R": 0.0,
          "G": 0.0,
          "B": 1.0,
          "A": 1.0,
          "R8": 0,
          "G8": 0,
          "B8": 255,
          "A8": 255,
          "H": 0.6666667,
          "S": 1.0,
          "V": 1.0,
          "Luminance": 0.0722
        },
        "graphicSize": {
          "X": 16,
          "Y": 16
        }
      },
      "statSheet": {
        "Stats": {
          "fertility": {
            "defName": "fertility",
            "description": "The tile's fertility",
            "Type": "Undefined",
            "baseValue": 0.0
          }
        },
        "StatModifers": {
          "Move Speed": {
            "defName": "MoveSpeed Modifier",
            "description": "Tiles effect on Move Speed",
            "modifierType": "Flat",
            "targetStat": "Move Speed",
            "value": 0.5
          }
        }
      },
      "defName": "Shallow Ocean",
      "description": "it's Ocean which is shallow"
    },
    "Shallow Water": {
      "collidable": false,
      "supportProvided": "Medium",
      "supportReq": "None",
      "graphicData": {
        "texturePath": "terrain/natural/water",
        "variants": 1,
        "color": {
          "R": 0.6784314,
          "G": 0.84705883,
          "B": 0.9019608,
          "A": 1.0,
          "R8": 173,
          "G8": 216,
          "B8": 230,
          "A8": 255,
          "H": 0.5409357,
          "S": 0.24782607,
          "V": 0.9019608,
          "Luminance": 0.8151726
        },
        "graphicSize": {
          "X": 16,
          "Y": 16
        }
      },
      "statSheet": {
        "Stats": {
          "fertility": {
            "defName": "fertility",
            "description": "The tile's fertility",
            "Type": "Undefined",
            "baseValue": 0.0
          }
        },
        "StatModifers": {
          "Move Speed": {
            "defName": "MoveSpeed Modifier",
            "description": "Tiles effect on Move Speed",
            "modifierType": "Flat",
            "targetStat": "Move Speed",
            "value": 0.5
          }
        }
      },
      "defName": "Shallow Water",
      "description": "it's shallow water"
    },
    "Deep Ocean": {
      "collidable": false,
      "supportProvided": "None",
      "supportReq": "None",
      "graphicData": {
        "texturePath": "terrain/natural/ocean",
        "variants": 1,
        "color": {
          "R": 0.0,
          "G": 0.0,
          "B": 0.54509807,
          "A": 1.0,
          "R8": 0,
          "G8": 0,
          "B8": 139,
          "A8": 255,
          "H": 0.6666667,
          "S": 1.0,
          "V": 0.54509807,
          "Luminance": 0.03935608
        },
        "graphicSize": {
          "X": 16,
          "Y": 16
        }
      },
      "statSheet": {
        "Stats": {
          "fertility": {
            "defName": "fertility",
            "description": "The tile's fertility",
            "Type": "Undefined",
            "baseValue": 0.0
          }
        },
        "StatModifers": {
          "Move Speed": {
            "defName": "MoveSpeed Modifier",
            "description": "Tiles effect on Move Speed",
            "modifierType": "Flat",
            "targetStat": "Move Speed",
            "value": 0.0
          }
        }
      },
      "defName": "Deep Ocean",
      "description": "it's Ocean which is Deep"
    },
    "Deep Water": {
      "collidable": false,
      "supportProvided": "None",
      "supportReq": "None",
      "graphicData": {
        "texturePath": "terrain/natural/water",
        "variants": 1,
        "color": {
          "R": 0.25490198,
          "G": 0.4117647,
          "B": 0.88235295,
          "A": 1.0,
          "R8": 65,
          "G8": 105,
          "B8": 225,
          "A8": 255,
          "H": 0.625,
          "S": 0.71111107,
          "V": 0.88235295,
          "Luminance": 0.41239217
        },
        "graphicSize": {
          "X": 16,
          "Y": 16
        }
      },
      "statSheet": {
        "Stats": {
          "fertility": {
            "defName": "fertility",
            "description": "The tile's fertility",
            "Type": "Undefined",
            "baseValue": 0.0
          }
        },
        "StatModifers": {
          "Move Speed": {
            "defName": "MoveSpeed Modifier",
            "description": "Tiles effect on Move Speed",
            "modifierType": "Flat",
            "targetStat": "Move Speed",
            "value": 0.2
          }
        }
      },
      "defName": "Deep Water",
      "description": "it's deep water, which you have to swim through"
    }
  }
}