{
  "render distance": 64.0,
  "generation settings": {
    "world size": {
      "X": 32,
      "Y": 32 
    },
    "world seed": 8,
    "map zoom": 1,
    "seaLevel": -0.3,
    "mountainSize": 0.3,
    "elevation settings": {
      "octaves": 6,
      "frequency": 0.02,
      "persistence": 0.4,
      "lacunarity": 2.6,
      "fractalType": 1,
      "noiseType": 1
    },
    "temperature settings": {
      "octaves": 6,
      "frequency": 0.017,
      "persistence": 0.4,
      "lacunarity": 2.6,
      "fractalType": 1,
      "noiseType": 1
    },
    "moisture settings": {
      "octaves": 8,
      "frequency": 0.01,
      "persistence": 0.5,
      "lacunarity": 2,
      "fractalType": 1,
      "noiseType": 1
    }
  }
}